main.py
kedongdong-0.3.dist-info/METADATA
kedongdong-0.3.dist-info/WHEEL
kedongdong-0.3.dist-info/top_level.txt
kedongdong-0.3.dist-info/RECORD
