Metadata-Version: 2.1
Name: kedongdong
Version: 0.3
Summary: kedongdong is the best fruit
Author-email: alin <vydhaalin@gmail.com>
Project-URL: Homepage, https://github.com/alinnezha/kedongdong
Project-URL: repository, https://github.com/alinnezha/kedongdong
Classifier: Programming Language :: Python :: 3
Classifier: License :: OSI Approved :: MIT License
Classifier: Operating System :: OS Independent
Requires-Python: >=3.8
Requires-Dist: matchaxyz ==0.3
Requires-Dist: atomicalsr ==0.4
